__main__.py
flaskhost/__init__.py
flaskhost/cli.py
flaskhost-0.0.1.dist-info/METADATA
flaskhost-0.0.1.dist-info/WHEEL
flaskhost-0.0.1.dist-info/entry_points.txt
flaskhost-0.0.1.dist-info/top_level.txt
flaskhost-0.0.1.dist-info/zip-safe
flaskhost-0.0.1.dist-info/RECORD
